{
    "__comment_:trans": "This translation will be available for the entire Component",
    "trans": {
        "de": {
            "Hello Component": "Hallo-Komponente",
            "Component showcase": "Komponentenubersicht",
            "A complete visual example with snippets, AJAX and Bootstrap modals.": "Ein vollstandiges visuelles Beispiel mit Snippets, AJAX und Bootstrap-Modals.",
            "Open test route one": "Testroute eins offnen",
            "Open test route two": "Testroute zwei offnen",
            "Global snippet": "Globales Snippet",
            "Available in all application routes.": "In allen Anwendungsrouten verfugbar.",
            "Component route snippet": "Komponentenrouten-Snippet",
            "Available in all routes of this component.": "In allen Routen dieser Komponente verfugbar.",
            "Rendered below in full width": "Unten in voller Breite dargestellt",
            "Current route snippet": "Aktuelles Routen-Snippet",
            "Available only in this exact route.": "Nur in dieser genauen Route verfugbar.",
            "This snippet belongs only to this page.": "Dieses Snippet gehort nur zu dieser Seite.",
            "Route snippet for the full component": "Routen-Snippet fur die gesamte Komponente",
            "This block is available for all routes in this component.": "Dieser Block ist fur alle Routen dieser Komponente verfugbar.",
            "AJAX example": "AJAX-Beispiel",
            "Load content via AJAX": "Inhalt per AJAX laden",
            "Press the button to load AJAX content.": "Drucken Sie die Schaltflache, um AJAX-Inhalt zu laden.",
            "AJAX content loaded": "AJAX-Inhalt geladen",
            "This block was rendered by route /ajax/example.": "Dieser Block wurde von der Route /ajax/example gerendert.",
            "Bootstrap modal examples": "Bootstrap-Modal-Beispiele",
            "Open simple modal": "Einfaches Modal offnen",
            "Open AJAX modal": "AJAX-Modal offnen",
            "Open modal with form": "Modal mit Formular offnen",
            "Simple modal": "Einfaches Modal",
            "This is a plain Bootstrap 5 modal without extra CSS.": "Dies ist ein einfaches Bootstrap-5-Modal ohne zusatzliches CSS.",
            "Close": "Schliessen",
            "Modal with AJAX": "Modal mit AJAX",
            "Load modal content": "Modalinhalt laden",
            "Click to load content from an AJAX endpoint.": "Klicken Sie, um Inhalt von einem AJAX-Endpunkt zu laden.",
            "Modal AJAX loaded successfully.": "AJAX-Modalinhalt erfolgreich geladen.",
            "You are viewing dynamic content coming from /ajax/modal-content.": "Sie sehen dynamischen Inhalt von /ajax/modal-content.",
            "Modal with form": "Modal mit Formular",
            "This form sends data to route /test2 to demonstrate form handling.": "Dieses Formular sendet Daten an die Route /test2, um die Formularverarbeitung zu demonstrieren.",
            "Name": "Name",
            "Your name": "Ihr Name",
            "Topic": "Thema",
            "Snippets": "Snippets",
            "Modals": "Modals",
            "Send form": "Formular senden",
            "Test One": "Test Eins",
            "Test Two": "Test Zwei",
            "Back to home": "Zur Startseite",
            "This route uses the custom dispatcher class.": "Diese Route verwendet die benutzerdefinierte Dispatcher-Klasse.",
            "dispatch_result": "dispatch_result",
            "foo value": "foo-Wert",
            "This route receives GET data from the modal form.": "Diese Route empfangt GET-Daten aus dem Modalformular.",
            "ref:example:reference": "Dies ist ein Referenztext fur die Ubersetzung.",
            "Open AJAX modal (auto)": "AJAX-Modal (auto) offnen",
            "Modal with AJAX (auto)": "Modal mit AJAX (auto)",
            "Loading modal content...": "Modalinhalt wird geladen..."
        }
    }
}
