{
    "__comment_:trans": "This translation will be available for the entire Component",
    "trans": {
        "el": {
            "A complete visual example with snippets, AJAX and Bootstrap modals.": "Ένα πλήρες οπτικό παράδειγμα με αποσπάσματα, AJAX και Bootstrap modals.",
            "AJAX content loaded": "Περιεχόμενο AJAX φορτώθηκε",
            "AJAX example": "Παράδειγμα AJAX",
            "Available in all application routes.": "Διαθέσιμο σε όλες τις διαδρομές της εφαρμογής.",
            "Available in all routes of this component.": "Διαθέσιμο σε όλες τις διαδρομές αυτού του στοιχείου.",
            "Available only in this exact route.": "Διαθέσιμο μόνο σε αυτή την ακριβή διαδρομή.",
            "Back to home": "Πίσω στο σπίτι",
            "Bootstrap modal examples": "Παραδείγματα Bootstrap modal",
            "Click to load content from an AJAX endpoint.": "Κάντε κλικ για να φορτώσετε περιεχόμενο από ένα AJAX endpoint.",
            "Close": "Κλείσιμο",
            "Component route snippet": "Απόσπασμα διαδρομής στοιχείου",
            "Component showcase": "Παρουσίαση στοιχείου",
            "Current route snippet": "Τρέχον απόσπασμα διαδρομής",
            "dispatch_result": "αποτέλεσμα_dispatch",
            "foo value": "τιμή foo",
            "Global snippet": "Γενικό απόσπασμα",
            "Hello Component": "Στοιχείο Hello",
            "Load content via AJAX": "Φόρτωση περιεχομένου μέσω AJAX",
            "Load modal content": "Φόρτωση περιεχομένου modal",
            "Loading modal content...": "Φόρτωση περιεχομένου modal...",
            "Modal AJAX loaded successfully.": "Modal AJAX φορτώθηκε επιτυχώς.",
            "Modal with AJAX": "Modal με AJAX",
            "Modal with AJAX (auto)": "Modal με AJAX (auto)",
            "Modal with form": "Modal με φόρμα",
            "Modals": "Modals",
            "Name": "Όνομα",
            "Open AJAX modal": "Άνοιγμα AJAX modal",
            "Open AJAX modal (auto)": "Άνοιγμα AJAX modal (auto)",
            "Open modal with form": "Άνοιγμα modal με φόρμα",
            "Open simple modal": "Άνοιγμα απλού modal",
            "Open test route one": "Άνοιγμα διαδρομής δοκιμής ένα",
            "Open test route two": "Άνοιγμα διαδρομής δοκιμής δύο",
            "Press the button to load AJAX content.": "Πατήστε το κουμπί για να φορτώσετε περιεχόμενο AJAX.",
            "ref:example:reference": "Αυτό είναι ένα κείμενο αναφοράς για μετάφραση.",
            "Rendered below in full width": "Αποδόθηκε παρακάτω σε πλήρη πλάτος",
            "Route snippet for the full component": "Απόσπασμα διαδρομής για το πλήρες στοιχείο",
            "Send form": "Αποστολή φόρμας",
            "Simple modal": "Απλό modal",
            "Snippets": "Αποσπάσματα",
            "Test One": "Δοκιμή Ένα",
            "Test Two": "Δοκιμή Δύο",
            "This block is available for all routes in this component.": "Αυτό το μπλοκ είναι διαθέσιμο για όλες τις διαδρομές σε αυτό το στοιχείο.",
            "This block was rendered by route /ajax/example.": "Αυτό το μπλοκ αποδόθηκε από τη διαδρομή /ajax/example.",
            "This form sends data to route /test2 to demonstrate form handling.": "Αυτή η φόρμα στέλνει δεδομένα στη διαδρομή /test2 για να δείξει τη διαχείριση φορμών.",
            "This is a plain Bootstrap 5 modal without extra CSS.": "Αυτό είναι ένα απλό Bootstrap 5 modal χωρίς επιπλέον CSS.",
            "This route receives GET data from the modal form.": "Αυτή η διαδρομή λαμβάνει δεδομένα GET από τη φόρμα modal.",
            "This route uses the custom dispatcher class.": "Αυτή η διαδρομή χρησιμοποιεί την προσαρμοσμένη κλάση dispatcher.",
            "This snippet belongs only to this page.": "Αυτό το απόσπασμα ανήκει μόνο σε αυτή τη σελίδα.",
            "Topic": "Θέμα",
            "You are viewing dynamic content coming from /ajax/modal-content.": "Βλέπετε δυναμικό περιεχόμενο που προέρχεται από /ajax/modal-content.",
            "Your name": "Το όνομά σας"
        }
    }
}
